lapixdl/__init__.py
lapixdl/__main__.py
lapixdl/base.py
lapixdl/convert.py
lapixdl/commands/__init__.py
lapixdl/commands/converter.py
lapixdl/commands/main.py
lapixdl/evaluation/__init__.py
lapixdl/evaluation/evaluate.py
lapixdl/evaluation/model.py
lapixdl/evaluation/plot.py
lapixdl/evaluation/visualize.py
lapixdl/formats/__init__.py
lapixdl/formats/annotation.py
lapixdl/formats/labelbox.py
lapixdl/formats/lapix.py
lapixdl/formats/mask.py
lapixdl-0.11.0.dist-info/LICENCE
lapixdl-0.11.0.dist-info/METADATA
lapixdl-0.11.0.dist-info/WHEEL
lapixdl-0.11.0.dist-info/entry_points.txt
lapixdl-0.11.0.dist-info/top_level.txt
lapixdl-0.11.0.dist-info/RECORD
