Metadata-Version: 2.1
Name: lapixdl
Version: 0.11.0
Summary: Utils for Computer Vision Deep Learning research
Home-page: https://github.com/lapix-ufsc/lapixdl
Author: LAPiX
License: MIT
Classifier: License :: OSI Approved :: MIT License
Classifier: Programming Language :: Python :: 3
Classifier: Programming Language :: Python :: 3 :: Only
Classifier: Programming Language :: Python :: Implementation :: CPython
Requires-Python: >=3.8
License-File: LICENCE
Requires-Dist: matplotlib
Requires-Dist: numpy
Requires-Dist: pandas
Requires-Dist: pillow
Requires-Dist: pyarrow
Requires-Dist: seaborn
Requires-Dist: shapely
Requires-Dist: tqdm
Requires-Dist: typing-extensions
